{"general__email.md":"a9663108","v1_guide_basic_configuration.md":"11e318f0","v1_guide_basic_frontend.md":"38a33121","v1_guide_basic_setup.md":"6d6190ee","general_support_support-me.md":"77b75863","general_changelog.md":"80e5aead","00_ todo_frontend.md":"971017c0","general_credits.md":"c5c0fccd","v1_guide_installation.md":"788a4551","general_report_security.md":"27a2bfaa","general_roadmap.md":"0bc361c5","general_contributing.md":"5d3aba3e","v1_definitions.md":"ff0f1da8","general_contact.md":"2c1abd0a","general_code_of_conduct.md":"956e03bd","general_support_donations.md":"a34180c4","00___todo.md":"f2a7ef3e","general_license.md":"62c97b26","generating.md":"793a7167","v1_introduction_what-is-promocode.md":"21d1d225","downloading - displaying images.md":"ff82226f","index.md":"d5b83eba"}
